minreal/__init__.py
minreal/app.py
minreal/client.py
minreal/csp.py
minreal/run.py
minreal/server.py
minreal/examples/__init__.py
minreal/examples/echo.py
minreal/examples/halvelife.py
minreal/examples/tcp.py
minreal/examples/tictactoe.py
minreal/static/csp.js
minreal/static/csp.js.bak
minreal/static/socket.js
minreal-0.4.2.dist-info/LICENSE
minreal-0.4.2.dist-info/METADATA
minreal-0.4.2.dist-info/WHEEL
minreal-0.4.2.dist-info/entry_points.txt
minreal-0.4.2.dist-info/top_level.txt
minreal-0.4.2.dist-info/RECORD
