Metadata-Version: 2.1
Name: minreal
Version: 0.4.2
Summary: A Python comet server build on CSP (Comet Session Protocol) and providing a TCP socket proxy.
Home-page: UNKNOWN
Author: Matthew Desmarais
Author-email: matthew.desmarais@gmail.com
License: MIT
Platform: UNKNOWN
Requires-Dist: paste
Requires-Dist: eventlet
Requires-Dist: webob
Requires-Dist: msgpack-python
